{
    "leagueRosters": {
        "progames": {},
        "teams": [
            {
                "slots": [
                    {
                        "player": {
                            "gameStarterStatus": -2147483648,
                            "sportsId": 5529,
                            "lastName": "Rivers",
                            "healthStatus": 0,
                            "droppable": true,
                            "jersey": "17",
                            "percentStarted": 41.30435,
                            "percentOwned": 82.80632,
                            "proTeamId": 24,
                            "tickerId": 1941774,
                            "lastNewsDate": "2018-01-01T01:13:15.000Z",
                            "isActive": true,
                            "isIREligible": false,
                            "draftRank": 142.2,
                            "lastVideoDate": "2017-12-17T08:03:23.677Z",
                            "playerId": 5529,
                            "percentChange": -0.05082,
                            "defaultPositionId": 1,
                            "value": -1,
                            "universeId": 1,
                            "eligibleSlotCategoryIds": [
                                0,
                                20
                            ],
                            "firstName": "Philip"
                        },
                        "watchList": false,
                        "isTradeLocked": false,
                        "opponentProTeamId": -1,
                        "slotCategoryId": 0,
                        "lockStatus": 4,
                        "isQueuedWaiverLocked": false
                    },
                    {
                        "player": {
                            "gameStarterStatus": -2147483648,
                            "sportsId": 2576434,
                            "lastName": "Gordon",
                            "healthStatus": 0,
                            "droppable": true,
                            "jersey": "28",
                            "percentStarted": 89.42652,
                            "percentOwned": 99.82079,
                            "proTeamId": 24,
                            "tickerId": 2576434,
                            "lastNewsDate": "2018-02-27T15:33:11.000Z",
                            "isActive": true,
                            "isIREligible": false,
                            "draftRank": 15.1,
                            "lastVideoDate": "2017-12-23T15:47:40.470Z",
                            "playerId": 17586,
                            "percentChange": 0.18979,
                            "defaultPositionId": 2,
                            "value": -1,
                            "universeId": 1,
                            "eligibleSlotCategoryIds": [
                                2,
                                23,
                                20
                            ],
                            "firstName": "Melvin"
                        },
                        "watchList": false,
                        "isTradeLocked": false,
                        "opponentProTeamId": -1,
                        "slotCategoryId": 2,
                        "lockStatus": 4,
                        "isQueuedWaiverLocked": false
                    },
                    {
                        "player": {
                            "gameStarterStatus": -2147483648,
                            "sportsId": 2980453,
                            "lastName": "Williams",
                            "healthStatus": 0,
                            "droppable": true,
                            "jersey": "30",
                            "percentStarted": 39.01274,
                            "percentOwned": 86.30573,
                            "proTeamId": 9,
                            "tickerId": 2980453,
                            "lastNewsDate": "2017-12-31T21:59:35.000Z",
                            "isActive": true,
                            "isIREligible": false,
                            "draftRank": 170,
                            "lastVideoDate": "2017-12-23T15:42:29.610Z",
                            "playerId": 18362,
                            "percentChange": 0.19462,
                            "defaultPositionId": 2,
                            "value": -1,
                            "universeId": 2,
                            "eligibleSlotCategoryIds": [
                                2,
                                23,
                                20
                            ],
                            "firstName": "Jamaal"
                        },
                        "watchList": false,
                        "isTradeLocked": false,
                        "opponentProTeamId": -1,
                        "slotCategoryId": 2,
                        "lockStatus": 4,
                        "isQueuedWaiverLocked": false
                    },
                    {
                        "player": {
                            "gameStarterStatus": -2147483648,
                            "sportsId": 13215,
                            "lastName": "Bryant",
                            "healthStatus": 0,
                            "droppable": true,
                            "jersey": "88",
                            "percentStarted": 60.18307,
                            "percentOwned": 98.627,
                            "proTeamId": 6,
                            "tickerId": 2268475,
                            "lastNewsDate": "2018-01-23T23:51:02.000Z",
                            "isActive": true,
                            "isIREligible": false,
                            "draftRank": 26.4,
                            "lastVideoDate": "2017-12-28T17:51:11.853Z",
                            "playerId": 13215,
                            "percentChange": -0.08386,
                            "defaultPositionId": 3,
                            "value": -1,
                            "universeId": 2,
                            "eligibleSlotCategoryIds": [
                                4,
                                23,
                                20
                            ],
                            "firstName": "Dez"
                        },
                        "watchList": false,
                        "isTradeLocked": false,
                        "opponentProTeamId": -1,
                        "slotCategoryId": 4,
                        "lockStatus": 4,
                        "isQueuedWaiverLocked": false
                    },
                    {
                        "player": {
                            "gameStarterStatus": -2147483648,
                            "sportsId": 15839,
                            "lastName": "Goodwin",
                            "healthStatus": 0,
                            "droppable": true,
                            "jersey": "11",
                            "percentStarted": 28.10458,
                            "percentOwned": 70.45752,
                            "proTeamId": 25,
                            "tickerId": 2467368,
                            "lastNewsDate": "2018-01-01T01:10:11.000Z",
                            "isActive": true,
                            "isIREligible": false,
                            "draftRank": 170,
                            "lastVideoDate": "2017-12-21T19:39:26.150Z",
                            "playerId": 15839,
                            "percentChange": 0.06513,
                            "defaultPositionId": 3,
                            "value": -1,
                            "universeId": 2,
                            "eligibleSlotCategoryIds": [
                                4,
                                23,
                                20
                            ],
                            "firstName": "Marquise"
                        },
                        "watchList": false,
                        "isTradeLocked": false,
                        "opponentProTeamId": -1,
                        "slotCategoryId": 4,
                        "lockStatus": 4,
                        "isQueuedWaiverLocked": false
                    },
                    {
                        "player": {
                            "gameStarterStatus": -2147483648,
                            "sportsId": 13229,
                            "lastName": "Gronkowski",
                            "healthStatus": 0,
                            "droppable": true,
                            "jersey": "87",
                            "percentStarted": 92.9368,
                            "percentOwned": 99.81413,
                            "proTeamId": 17,
                            "tickerId": 2267819,
                            "lastNewsDate": "2018-02-05T05:59:07.000Z",
                            "isActive": true,
                            "isIREligible": false,
                            "draftRank": 21.4,
                            "lastVideoDate": "2018-01-17T01:05:55.110Z",
                            "playerId": 13229,
                            "percentChange": -0.01752,
                            "defaultPositionId": 4,
                            "value": -1,
                            "universeId": 1,
                            "eligibleSlotCategoryIds": [
                                6,
                                23,
                                20
                            ],
                            "firstName": "Rob"
                        },
                        "watchList": false,
                        "isTradeLocked": false,
                        "opponentProTeamId": -1,
                        "slotCategoryId": 6,
                        "lockStatus": 4,
                        "isQueuedWaiverLocked": false
                    },
                    {
                        "player": {
                            "gameStarterStatus": -2147483648,
                            "sportsId": 16040,
                            "lastName": "Anderson",
                            "healthStatus": 0,
                            "droppable": true,
                            "jersey": "22",
                            "percentStarted": 30.33932,
                            "percentOwned": 84.43114,
                            "proTeamId": 7,
                            "tickerId": 2576853,
                            "lastNewsDate": "2018-01-11T05:34:25.000Z",
                            "isActive": true,
                            "isIREligible": false,
                            "draftRank": 74.4,
                            "lastVideoDate": "2017-12-31T13:41:28.710Z",
                            "playerId": 16040,
                            "percentChange": 0.59655,
                            "defaultPositionId": 2,
                            "value": -1,
                            "universeId": 1,
                            "eligibleSlotCategoryIds": [
                                2,
                                23,
                                20
                            ],
                            "firstName": "C.J."
                        },
                        "watchList": false,
                        "isTradeLocked": false,
                        "opponentProTeamId": -1,
                        "slotCategoryId": 23,
                        "lockStatus": 4,
                        "isQueuedWaiverLocked": false
                    },
                    {
                        "player": {
                            "gameStarterStatus": -2147483648,
                            "sportsId": 60017,
                            "lastName": "D/ST",
                            "healthStatus": 0,
                            "droppable": true,
                            "percentStarted": 33.88889,
                            "percentOwned": 56.66667,
                            "proTeamId": 17,
                            "tickerId": 0,
                            "lastNewsDate": "1970-01-01T00:00:00.000Z",
                            "isActive": true,
                            "isIREligible": false,
                            "draftRank": 147.3,
                            "lastVideoDate": "2016-01-14T04:37:24.343Z",
                            "playerId": 60017,
                            "percentChange": 0.65644,
                            "defaultPositionId": 16,
                            "value": -1,
                            "universeId": 1,
                            "eligibleSlotCategoryIds": [
                                16,
                                20
                            ],
                            "firstName": "Patriots"
                        },
                        "watchList": false,
                        "isTradeLocked": false,
                        "opponentProTeamId": -1,
                        "slotCategoryId": 16,
                        "lockStatus": 4,
                        "isQueuedWaiverLocked": false
                    },
                    {
                        "player": {
                            "gameStarterStatus": -2147483648,
                            "sportsId": 11122,
                            "lastName": "Prater",
                            "healthStatus": 0,
                            "droppable": true,
                            "jersey": "5",
                            "percentStarted": 65.21739,
                            "percentOwned": 75.25084,
                            "proTeamId": 8,
                            "tickerId": 2276480,
                            "lastNewsDate": "2018-01-01T19:48:49.000Z",
                            "isActive": true,
                            "isIREligible": false,
                            "draftRank": 143.9,
                            "lastVideoDate": "1970-01-01T00:00:00.000Z",
                            "playerId": 11122,
                            "percentChange": -1.38734,
                            "defaultPositionId": 5,
                            "value": -1,
                            "universeId": 2,
                            "eligibleSlotCategoryIds": [
                                17,
                                20
                            ],
                            "firstName": "Matt"
                        },
                        "watchList": false,
                        "isTradeLocked": false,
                        "opponentProTeamId": -1,
                        "slotCategoryId": 17,
                        "lockStatus": 4,
                        "isQueuedWaiverLocked": false
                    },
                    {
                        "player": {
                            "gameStarterStatus": -2147483648,
                            "sportsId": 15795,
                            "lastName": "Hopkins",
                            "healthStatus": 2,
                            "droppable": true,
                            "jersey": "10",
                            "percentStarted": 84.43316,
                            "percentOwned": 97.46193,
                            "proTeamId": 34,
                            "tickerId": 2512410,
                            "lastNewsDate": "2018-01-09T22:24:00.000Z",
                            "isActive": true,
                            "isIREligible": false,
                            "draftRank": 28.7,
                            "lastVideoDate": "2017-12-31T13:46:22.673Z",
                            "playerId": 15795,
                            "percentChange": -0.00831,
                            "defaultPositionId": 3,
                            "value": -1,
                            "universeId": 1,
                            "eligibleSlotCategoryIds": [
                                4,
                                23,
                                20
                            ],
                            "firstName": "DeAndre"
                        },
                        "watchList": false,
                        "isTradeLocked": false,
                        "opponentProTeamId": -1,
                        "slotCategoryId": 20,
                        "lockStatus": 4,
                        "isQueuedWaiverLocked": false
                    },
                    {
                        "player": {
                            "gameStarterStatus": -2147483648,
                            "sportsId": 14129,
                            "lastName": "Powell",
                            "healthStatus": 0,
                            "droppable": true,
                            "jersey": "29",
                            "percentStarted": 16.23529,
                            "percentOwned": 69.17647,
                            "proTeamId": 20,
                            "tickerId": 2266049,
                            "lastNewsDate": "2018-02-19T05:23:22.000Z",
                            "isActive": true,
                            "isIREligible": false,
                            "draftRank": 56.2,
                            "lastVideoDate": "2017-12-30T06:32:01.027Z",
                            "playerId": 14129,
                            "percentChange": -0.6152,
                            "defaultPositionId": 2,
                            "value": -1,
                            "universeId": 1,
                            "eligibleSlotCategoryIds": [
                                2,
                                23,
                                20
                            ],
                            "firstName": "Bilal"
                        },
                        "watchList": false,
                        "isTradeLocked": false,
                        "opponentProTeamId": -1,
                        "slotCategoryId": 20,
                        "lockStatus": 4,
                        "isQueuedWaiverLocked": false
                    },
                    {
                        "player": {
                            "gameStarterStatus": -2147483648,
                            "sportsId": 3122840,
                            "lastName": "Watson",
                            "healthStatus": 2,
                            "droppable": true,
                            "jersey": "4",
                            "percentStarted": 23.99608,
                            "percentOwned": 55.14202,
                            "proTeamId": 34,
                            "tickerId": 3122840,
                            "lastNewsDate": "2018-02-05T23:54:31.000Z",
                            "isActive": true,
                            "isIREligible": false,
                            "draftRank": 68,
                            "lastVideoDate": "2017-12-31T13:43:10.127Z",
                            "playerId": 18246,
                            "percentChange": -0.04875,
                            "defaultPositionId": 1,
                            "value": -1,
                            "universeId": 1,
                            "eligibleSlotCategoryIds": [
                                0,
                                20
                            ],
                            "firstName": "Deshaun"
                        },
                        "watchList": false,
                        "isTradeLocked": false,
                        "opponentProTeamId": -1,
                        "slotCategoryId": 20,
                        "lockStatus": 4,
                        "isQueuedWaiverLocked": false
                    },
                    {
                        "player": {
                            "gameStarterStatus": -2147483648,
                            "sportsId": 16886,
                            "lastName": "Bryant",
                            "healthStatus": 0,
                            "droppable": true,
                            "jersey": "10",
                            "percentStarted": 15.51433,
                            "percentOwned": 73.01855,
                            "proTeamId": 23,
                            "tickerId": 2512195,
                            "lastNewsDate": "2018-01-14T22:49:21.000Z",
                            "isActive": true,
                            "isIREligible": false,
                            "draftRank": 67.1,
                            "lastVideoDate": "2017-12-31T13:45:30.403Z",
                            "playerId": 16886,
                            "percentChange": -1.65771,
                            "defaultPositionId": 3,
                            "value": -1,
                            "universeId": 1,
                            "eligibleSlotCategoryIds": [
                                4,
                                23,
                                20
                            ],
                            "firstName": "Martavis"
                        },
                        "watchList": false,
                        "isTradeLocked": false,
                        "opponentProTeamId": -1,
                        "slotCategoryId": 20,
                        "lockStatus": 4,
                        "isQueuedWaiverLocked": false
                    },
                    {
                        "player": {
                            "gameStarterStatus": -2147483648,
                            "sportsId": 17452,
                            "lastName": "Oliver",
                            "healthStatus": 0,
                            "droppable": true,
                            "jersey": "32",
                            "percentStarted": 0,
                            "percentOwned": 2.90909,
                            "proTeamId": 24,
                            "tickerId": 2470277,
                            "lastNewsDate": "2018-01-03T20:18:54.000Z",
                            "isActive": true,
                            "isIREligible": false,
                            "draftRank": 170,
                            "lastVideoDate": "1970-01-01T00:00:00.000Z",
                            "playerId": 17143,
                            "percentChange": -1.78347,
                            "defaultPositionId": 2,
                            "value": -1,
                            "universeId": 1,
                            "eligibleSlotCategoryIds": [
                                2,
                                23,
                                20
                            ],
                            "firstName": "Branden"
                        },
                        "watchList": false,
                        "isTradeLocked": false,
                        "opponentProTeamId": -1,
                        "slotCategoryId": 20,
                        "lockStatus": 4,
                        "isQueuedWaiverLocked": false
                    },
                    {
                        "player": {
                            "gameStarterStatus": -2147483648,
                            "sportsId": 15994,
                            "lastName": "Riddick",
                            "healthStatus": 0,
                            "droppable": true,
                            "jersey": "25",
                            "percentStarted": 13.08642,
                            "percentOwned": 60.24691,
                            "proTeamId": 8,
                            "tickerId": 2469222,
                            "lastNewsDate": "2018-01-08T04:08:29.000Z",
                            "isActive": true,
                            "isIREligible": false,
                            "draftRank": 78,
                            "lastVideoDate": "2017-12-22T14:14:41.210Z",
                            "playerId": 15994,
                            "percentChange": -1.35829,
                            "defaultPositionId": 2,
                            "value": -1,
                            "universeId": 2,
                            "eligibleSlotCategoryIds": [
                                2,
                                23,
                                20
                            ],
                            "firstName": "Theo"
                        },
                        "watchList": false,
                        "isTradeLocked": false,
                        "opponentProTeamId": -1,
                        "slotCategoryId": 20,
                        "lockStatus": 4,
                        "isQueuedWaiverLocked": false
                    },
                    {
                        "player": {
                            "gameStarterStatus": -2147483648,
                            "sportsId": 3045127,
                            "lastName": "Gallman",
                            "healthStatus": 0,
                            "droppable": true,
                            "jersey": "22",
                            "percentStarted": 3.97878,
                            "percentOwned": 37.40053,
                            "proTeamId": 19,
                            "tickerId": 3045127,
                            "lastNewsDate": "2017-12-31T22:30:43.000Z",
                            "isActive": true,
                            "isIREligible": false,
                            "draftRank": 170,
                            "lastVideoDate": "2017-12-30T06:28:47.730Z",
                            "playerId": 18233,
                            "percentChange": 1.01469,
                            "defaultPositionId": 2,
                            "value": -1,
                            "universeId": 2,
                            "eligibleSlotCategoryIds": [
                                2,
                                23,
                                20
                            ],
                            "firstName": "Wayne"
                        },
                        "watchList": false,
                        "isTradeLocked": false,
                        "opponentProTeamId": -1,
                        "slotCategoryId": 20,
                        "lockStatus": 4,
                        "isQueuedWaiverLocked": false
                    }
                ],
                "team": {
                    "divisionStanding": 2,
                    "overallStanding": 3,
                    "waiverRank": 8,
                    "division": {
                        "divisionName": "East",
                        "divisionId": 0,
                        "size": 5
                    },
                    "teamAbbrev": "SNAP",
                    "teamNickname": "be Darned",
                    "logoUrl": "https://i.imgflip.com/1wght6.jpg",
                    "teamLocation": "Billal",
                    "teamId": 7,
                    "logoType": "customValid"
                },
                "teamId": 7
            }
        ],
        "scoringPeriodId": 18
    },
    "metadata": {
        "leagueId": "286565",
        "defaults": {},
        "status": "offseason",
        "dateModifiedLeague": "2018-04-13T08:38:22.077Z",
        "seasonId": "2017",
        "serverDate": "2018-04-26T21:15:19.149Z"
    }
}